{
  "buyChain": "solana",
  "sellChain": "ethereum",
  "buyPrice": 0.102688,
  "sellPrice": 2292.836642,
  "buyDex": "jupiter",
  "sellDex": "uniswap-v3",
  "profitPercentage": 2232718.481224681,
  "priceDiff": 2292.7339540000003,
  "tradeSize": 1000,
  "profitUsd": 22327184.812246807,
  "timestamp": 1770125013756,
  "source": "ARBITRAGE_DETECTOR",
  "tradeLink": "https://phantom.app/",
  "platformName": "Phantom",
  "success": true,
  "buyResult": {
    "success": true,
    "dryRun": true,
    "signature": "dry-run-signature"
  },
  "sellResult": {
    "base": "ETH",
    "quote": "USDT",
    "amount": 9738.236210657526,
    "symbol": "ETHUSDT",
    "orderId": "dry-run-id",
    "transactTime": 1770125013756,
    "status": "FILLED_DRY_RUN"
  },
  "gasCosts": {
    "buy": {
      "chain": "solana",
      "gasCostNative": 0.00001,
      "gasCostUsd": 0.00000102696
    },
    "sell": {
      "chain": "ethereum",
      "gasCostNative": 0.0054,
      "gasCostUsd": 13.5
    },
    "totalUsd": 13.50000102696
  },
  "netProfit": 22327171.31224578,
  "executionTimeMs": 479,
  "dryRun": true
}